{"file:///G:/Temp/TECHNO":{"assets/images/hashes.json":"fuXp5iWOCeTsNniaJX+ZZg==","assets/images/logo.png":"GUQx7o/EJ1oiW18oWyeA9w==","assets/images/mbr-1500x1000.jpg":"SwZU3dYEtKYeTRpjUofixg==","assets/images/img-20240805-wa0024-1000x1000.jpg":"Xf9GHWmjrRlVwfrFE+phQA==","assets/images/picture1-480x437.jpg":"pvdPNmczXDvXmZ7/JCPz0Q==","assets/images/fozia-1833x3000.jpeg":"0+ZZkihCJPE8TIJk58OaAw==","assets/images/screenshot-2025-04-10-203001-557x584.png":"FdT6du15ireGxpM0W0l4dw==","assets/images/467492970-8910119419038273-5347515059480454155-n-480x480.jpeg":"ztibNRwzk+JGi8xibkstug==","assets/images/traditional-greek-salad-recipe-3-505x337.jpg":"f2yepBMdruowO1mk78wvMQ==","assets/images/img-8477-jpg-1-505x673.jpg":"wA/A7PQCt8jQF3QSNvJLkA==","assets/images/4905-1-1723229216-505x505.png":"L+Fpy9CG9S0XT/nIhtCS9A==","assets/images/falafel-16-505x758.jpg":"qGpZH/ViF0xbNeBhOPmi8w==","assets/images/k-archive-3b432b41ce04c96a08d77befa42b9881a587a436-505x632.jpg":"CFSiD0bUYOG2WjpVag444g==","assets/images/chicken-biryani-505x757.jpg":"hbnJoqLo2EuIJpp5NtSrnA==","assets/images/butter-chicken.-ss.-low-res-476x476.jpg":"TySZCjoqPaLR1vHcNnBAzQ==","assets/images/restaurant-style-dal-makhani-505x765.jpg":"BsL0U7bqPHidPOB0K5GMFw==","assets/images/7499757jollofricechefjohn4x3-d601da10d7e845d1ad4c8656a5b87ed4-505x379.jpg":"ryaS71Kk6w3yIvY/gWXyYQ==","assets/images/unnamed-505x505.jpg":"qbsscbinlnLFQmw+8IakYQ==","assets/images/beef-suya-exps-ft19-89779-f-1119-1-6-505x505.jpg":"wr8B7L9hAAyyvaETpEhC8Q==","assets/images/maxresdefault-505x284.jpg":"vr+YBwa6Eyo9bPD3iJcGpg==","assets/images/sushi-g7c97032b1-1280-505x337.jpg":"391WQpOp/sgrQewmVpxLbw==","assets/images/uncooked-dumplings-on-a-tray-scaled-505x505.jpg":"fO/4Bsg7jrsyG6TjGUJdSA==","assets/images/whole-cabbage-kimchi-505x399.jpg":"573eneQ8gfxlf5JPj0g+gw==","assets/images/190208-delish-ramen-horizontal-093-1550096715-505x379.jpg":"19bh9nRxOmnrfr8wN8iEFw==","assets/images/shop3.jpg":"pifu6efXMqhCcttDJuOW4A==","assets/images/shop11.jpg":"Bu6pAx52G/TYdzEHQwHEOA==","assets/images/mbr-1-160x240.jpg":"Y9huBL3MXwrRyiiLofyYjQ==","assets/images/mbr-160x240.jpg":"2g9Gf6w8ffUW9zmB39wDEg==","assets/images/mbr-160x96.jpg":"de6O9XzMhBCkOqFW4rt6og==","assets/images/mbr-160x160.png":"vI0at6ja59uhZiE4W3AtzA==","assets/images/mbr-1460x973.jpg":"XMFnZETIy8VO5eP3kAxUBQ==","assets/images/mbr-1920x1318.jpg":"9jXaoiwea6u2ewtWlz1XMg==","assets/images/mbr-1-1920x1280.jpg":"xUw5BLkR4yh6vkKvYoNPWA==","assets/images/35.webp":"wdrJ3EBMQOu9n8ck1oUIZg==","assets/images/38.webp":"JBmOWnvaKe7POOK8Yz5O0Q==","assets/images/39.jpg":"ydTLULiI50T2gk2u8v6NgQ==","assets/images/mbr-7.jpg":"ZwmjGMXHTeEuQVLLKjSvxw==","assets/images/mbr-1-180x120.jpg":"9HwyI3pYvf+AH5j8gS0gpA==","assets/images/husa-2000x1679.png":"EAqAik+sNDOhQDINUMOhEQ==","assets/images/35.jpg":"atK0W2jIUVP3drxLWZaH4g==","assets/images/36.jpg":"jcOgjNpbwa5Gw+Ra9Iqdog==","assets/images/37.jpg":"LZrCL+1TodNVvQ+jrSh7Pw==","assets/images/38.jpg":"aJJ2Uj6JWi/OkRNsYheLLw==","assets/images/32.jpg":"+JhkxAKMWRK7YrSTO24q4w==","assets/images/mbr-1920x1920.jpg":"VSGNpALF6zIU+vQhZGJUhw==","assets/web/assets/cookies-alert-plugin/cookies-alert-core.js":"Cv7piliGuFP6nqD4bPISSg==","assets/web/assets/cookies-alert-plugin/cookies-alert-script.js":"NCp/d5WwFLgvBEKzbors/A==","assets/bootstrap/css/bootstrap.min.css":"Ov4V6XZzTZ2qwmMQEQxFlA==","assets/bootstrap/css/bootstrap-grid.min.css":"B/UEMwCpd8W0hrWHLpycag==","assets/bootstrap/css/bootstrap-reboot.min.css":"Ui5OyWvr8teeN3hgkVQeIQ==","assets/bootstrap/js/bootstrap.min.js":"a+pgw0xdtnlxUGENrNxrzg==","assets/popper/popper.min.js":"NiE4ESlZe/NNSKniYj4FyQ==","assets/tether/tether.min.css":"YhVaOUjL8Xsb9LQHyQq4Tw==","assets/tether/tether.min.js":"PlC291/0Eo8keLHUT4D9+w==","assets/theme/css/style.css":"lC4G+ZBsMOSHmiAW82l6gQ==-VITbTf54ezV7Z7I/e4lZVw==","assets/smoothscroll/smooth-scroll.js":"1fU5SR6w/dKRUCNIywK1Sw==","assets/animatecss/animate.min.css":"F4tlGVjO/1VsvF81Xgi78Q==","assets/viewportchecker/jquery.viewportchecker.js":"BtceVK1754iA5BP1vmYP/Q==","assets/web/assets/jquery/jquery.min.js":"3F5/GMjTasHT1HU6h8mNCg==","assets/dropdown/css/style.css":"s+S8lVC62P0BWFtgHpaNFA==","assets/dropdown/js/nav-dropdown.js":"dC/upwyur9A4kPhFrRHwaQ==","assets/dropdown/js/navbar-dropdown.js":"ZePnAsEAv4Y5wJTD95L44g==","assets/touchswipe/jquery.touch-swipe.min.js":"9g/wVGnRdXmW2F9BctT/TQ==","assets/mbr-popup-btns/mbr-popup-btns.js":"g2GbrenJXG1arp60DOpQ0w==","assets/animate-css/css/animate.css":"zydBo6fqhCet5lFTOlTvGw==","assets/animate-css/css/animate.compat.css":"m7GKyT6jXMA+cWkcSvCVaA==","assets/animate-css/css/animate.min.css":"wL6OUyJqw0gz/ZtdvAHrxQ==","assets/animate-css/css/animation_utility.css":"wTLHeE1jaaLYVQ2qUERc6g==","assets/animate-css/js/oyethemes_onscroll_animation.js":"oFzZWLehhJVabE31f7TXfA==","assets/parallax/jarallax.min.js":"rX/x1RkUP0ZMvZZrsxrg7A==","assets/embla/embla.min.js":"+JN5fpraKrFLOFyg8FtNTg==","assets/embla/script.js":"4Ux7F4PHmWed/ig6tpNw0A==","assets/mobirise-tabs/mbr-tabs.js":"PdAH8AQnY6LdWKriaPl5/A==","assets/countdown/jquery.countdown.min.js":"nNeZtjQks/XXGgSH4kDhtg==","assets/mbr-switch-arrow/mbr-switch-arrow.js":"448Z9cq78UhKb3VOOwTusg==","assets/web/assets/mobirise-icons2/mobirise2.css":"+RO7OxVtE1FsD/N7V3/ADw==","assets/web/assets/mobirise-icons2/mobirise2.eot":"B2EjryGRojlTpzr1GHt3LQ==","assets/web/assets/mobirise-icons2/mobirise2.svg":"usCYAy7QdzckfeGReb9wWQ==","assets/web/assets/mobirise-icons2/mobirise2.ttf":"VMdAr7YYQ2ab9KiUyabAGA==","assets/web/assets/mobirise-icons2/mobirise2.woff":"xY3InaTfYGp0nlCuQBMudQ==","assets/formstyler/jquery.formstyler.css":"ajjp8ztH9eVUk4rdhVGFYg==","assets/formstyler/jquery.formstyler.js":"DOK+mP4W5Ag9IfhHtpWNMg==","assets/formstyler/jquery.formstyler.min.js":"AZwL++bNUiLJxmlnInDaEQ==","assets/formstyler/jquery.formstyler.theme.css":"J/V1s94HUkXblUKKORPI7w==","assets/datepicker/jquery.datetimepicker.min.css":"ho+tif2BPmsXNeoVpuhDPg==","assets/datepicker/jquery.datetimepicker.full.js":"ReJ4dJfeeDKs8i0ltGNWDQ==","assets/web/assets/mobirise-icons/mobirise-icons.css":"t/IrTIzfJvbDUoCV05F+7Q==","assets/web/assets/mobirise-icons/mobirise-icons.eot":"T9iJ+Vffe7n6Gk/+pf9gEw==","assets/web/assets/mobirise-icons/mobirise-icons.svg":"Yp5pSlGdnLgPdQLUa/Yv3w==","assets/web/assets/mobirise-icons/mobirise-icons.ttf":"r0OtN8kuMaYwUc+mlGDUWA==","assets/web/assets/mobirise-icons/mobirise-icons.woff":"3aYYVAIqADvsB1jjxJZ73w==","assets/socicon/css/styles.css":"q91aZJ04O5rzI1nJO9PRHw==","assets/socicon/fonts/socicon.eot":"MvYQV8XxgngrhGqjN3oHBw==","assets/socicon/fonts/socicon.svg":"U1iRKoyNjKeR+mUJr3QbXg==","assets/socicon/fonts/socicon.ttf":"IyAo3XNB2a/Q0ml3ZraPsQ==","assets/socicon/fonts/socicon.woff":"zQDjXd6bBUQi87pRsBWVqQ==","assets/socicon/fonts/socicon.woff2":"o3w8h99EHOwP99NXAoHpOQ==","assets/material-design/css/material-icons.min.css":"sGAJTEjS5eVti+O+V1Y0yg==","assets/material-design/fonts/MaterialIcons-Regular.eot":"UuRc/237QKSUIyTx1xIe6g==","assets/material-design/fonts/MaterialIcons-Regular.svg":"oa3qZVlMUC+dlCjxOuIQ4Q==","assets/material-design/fonts/MaterialIcons-Regular.ttf":"KPMR+vmHIOaMmDwFUxpsUw==","assets/material-design/fonts/MaterialIcons-Regular.woff":"pQSCoNNtFsBkGXPiX87MXg==","assets/material-design/fonts/MaterialIcons-Regular.woff2":"9PZteTfJ3IJJudMChoEglA==","assets/formoid/formoid.min.js":"NFW1BdnImhnEXiT1sMecQw=="}}